pulumi_splunk/__init__.py
pulumi_splunk/_inputs.py
pulumi_splunk/_utilities.py
pulumi_splunk/admin_saml_groups.py
pulumi_splunk/apps_local.py
pulumi_splunk/authentication_users.py
pulumi_splunk/authorization_roles.py
pulumi_splunk/configs_conf.py
pulumi_splunk/data_ui_views.py
pulumi_splunk/generic_acl.py
pulumi_splunk/global_http_event_collector.py
pulumi_splunk/indexes.py
pulumi_splunk/inputs_http_event_collector.py
pulumi_splunk/inputs_monitor.py
pulumi_splunk/inputs_script.py
pulumi_splunk/inputs_tcp_cooked.py
pulumi_splunk/inputs_tcp_raw.py
pulumi_splunk/inputs_tcp_splunk_tcp_token.py
pulumi_splunk/inputs_tcp_ssl.py
pulumi_splunk/inputs_udp.py
pulumi_splunk/lookup_definition.py
pulumi_splunk/lookup_table_file.py
pulumi_splunk/outputs.py
pulumi_splunk/outputs_tcp_default.py
pulumi_splunk/outputs_tcp_group.py
pulumi_splunk/outputs_tcp_server.py
pulumi_splunk/outputs_tcp_syslog.py
pulumi_splunk/provider.py
pulumi_splunk/pulumi-plugin.json
pulumi_splunk/py.typed
pulumi_splunk/saved_searches.py
pulumi_splunk/sh_indexes_manager.py
pulumi_splunk/config/__init__.py
pulumi_splunk/config/__init__.pyi
pulumi_splunk/config/vars.py
pulumi_splunk-1.2.24.dist-info/METADATA
pulumi_splunk-1.2.24.dist-info/WHEEL
pulumi_splunk-1.2.24.dist-info/top_level.txt
pulumi_splunk-1.2.24.dist-info/RECORD
